sinnia_utils/__init__.py
sinnia_utils/amqp.py
sinnia_utils/date_utils.py
sinnia_utils/string_utils.py
sinnia_utils/timezones.py
sinnia_utils/utils.py
sinnia_utils-0.1.1.dist-info/METADATA
sinnia_utils-0.1.1.dist-info/WHEEL
sinnia_utils-0.1.1.dist-info/RECORD
