Metadata-Version: 2.1
Name: sinnia-utils
Version: 0.1.1
Summary: 
Author: soniaseguz
Author-email: sonia.segura@sinnia.com
Requires-Python: >=3.9,<4.0
Classifier: Programming Language :: Python :: 3
Classifier: Programming Language :: Python :: 3.9
Classifier: Programming Language :: Python :: 3.10
Classifier: Programming Language :: Python :: 3.11
